cnext_server/.gitignore
cnext_server/__init__.py
cnext_server/__main__.py
cnext_server/public/404.html
cnext_server/public/_next/static/8KnY93POWcLvEaGxXR6az/_buildManifest.js
cnext_server/public/_next/static/8KnY93POWcLvEaGxXR6az/_ssgManifest.js
cnext_server/public/_next/static/chunks/269.60880de422ed31e1.js
cnext_server/public/_next/static/chunks/2852872c-257ebc72a8902899.js
cnext_server/public/_next/static/chunks/4ad82c5e-eacc478f45b94eba.js
cnext_server/public/_next/static/chunks/651.bfd69ea01d64d954.js
cnext_server/public/_next/static/chunks/660.2d01b32d8f282715.js
cnext_server/public/_next/static/chunks/741.25e0d543f796a94b.js
cnext_server/public/_next/static/chunks/75fc9c18-d4f616fecc6e1230.js
cnext_server/public/_next/static/chunks/866.cd5bfa886be4b007.js
cnext_server/public/_next/static/chunks/976-3cdeccab7a0db628.js
cnext_server/public/_next/static/chunks/e48519b3.c8db2bf231c5f0b8.js
cnext_server/public/_next/static/chunks/ed150ef9.8a701c53cbd4d124.js
cnext_server/public/_next/static/chunks/framework-0ba0ddd33199226d.js
cnext_server/public/_next/static/chunks/main-79e130091ee21132.js
cnext_server/public/_next/static/chunks/pages/_app-f9e7fff34d7b41e7.js
cnext_server/public/_next/static/chunks/pages/_error-c13976a61913457b.js
cnext_server/public/_next/static/chunks/pages/index-2ac4478fd0f61aa3.js
cnext_server/public/_next/static/chunks/polyfills-c67a75d1b6f99dc8.js
cnext_server/public/_next/static/chunks/webpack-0ca9a1df4831456a.js
cnext_server/public/_next/static/css/1b4f47eca4f664f1.css
cnext_server/public/_next/static/css/713625ab96f56113.css
cnext_server/public/_next/static/css/f0abbfc8cca2b2f0.css
cnext_server/public/favicon.ico
cnext_server/public/icons/cube-white.svg
cnext_server/public/icons/cube.svg
cnext_server/public/index.html
cnext_server/server/.dockerignore
cnext_server/server/Dockerfile
cnext_server/server/build/config.gypi
cnext_server/server/eventLog.js
cnext_server/server/ls/lsp_process.js
cnext_server/server/ls/streams.js
cnext-0.11.6.dist-info/entry_points.txt
cnext-0.11.6.dist-info/WHEEL
cnext-0.11.6.dist-info/METADATA
cnext-0.11.6.dist-info/RECORD
