Metadata-Version: 2.1
Name: cnext
Version: 0.11.6
Summary: The data-centric workspace for AI & DS
Home-page: https://cyc-ai.com/
License: MIT
Author: CycAI Inc
Requires-Python: >=3.9
Classifier: License :: OSI Approved :: MIT License
Classifier: Programming Language :: Python :: 3
Classifier: Programming Language :: Python :: 3.9
Classifier: Programming Language :: Python :: 3.10
Classifier: Programming Language :: Python :: 3.11
Requires-Dist: cnextlib (>=0.7.0,<0.8.0)
Requires-Dist: jupyter-client (>=7.4.5,<7.5.0)
Requires-Dist: jupyter-resource-usage (>=0.6.1,<0.7.0)
Requires-Dist: jupyterlab (>=3.4.0,<3.5.0)
Requires-Dist: matplotlib (>=3.5.1,<3.6.0)
Requires-Dist: matplotlib-inline (>=0.1.6,<0.2.0)
Requires-Dist: mlflow (>=1.30.0,<2.0.0)
Requires-Dist: multipledispatch (>=0.6.0,<0.7.0)
Requires-Dist: netron (>=6.0.0,<7.0.0)
Requires-Dist: pandas (>=1.3.5,<1.4.0)
Requires-Dist: plotly (>=5.7.0,<5.8.0)
Requires-Dist: protobuf (==3.20.1)
Requires-Dist: pyreadline (>=2.1,<3.0)
Requires-Dist: python-language-server (>=0.36.2,<0.37.0)
Requires-Dist: pyyaml (>=5.1,<6.0)
Requires-Dist: pyzmq (>=23.2.0,<24.0.0)
Requires-Dist: requests (>=2.27.1,<3.0.0)
Requires-Dist: send2trash (>=1.8.0,<2.0.0)
Requires-Dist: sentry-sdk (>=1.5.12,<2.0.0)
Requires-Dist: simplejson (>=3.17.6,<4.0.0)
